histoseg/__init__.py
histoseg/_version.py
histoseg/contours/__init__.py
histoseg/contours/pattern1_isoline.py
histoseg/gui/__init__.py
histoseg/gui/gui_app.py
histoseg/io/__init__.py
histoseg/io/huggingface.py
histoseg/sfplot/Searcher_Findee_Score.py
histoseg-0.1.7.dist-info/licenses/AUTHORS.rst
histoseg-0.1.7.dist-info/licenses/LICENSE
histoseg-0.1.7.dist-info/METADATA
histoseg-0.1.7.dist-info/WHEEL
histoseg-0.1.7.dist-info/top_level.txt
histoseg-0.1.7.dist-info/RECORD
