Metadata-Version: 2.4
Name: histoseg
Version: 0.1.7
Summary: ...
Author-email: Taobo Hu <taobo.hu@scilifelab.se>
License: Required Notice: Copyright (c) 2025 SPATHO AB.
Project-URL: Homepage, https://github.com/hutaobo/HistoSeg
Project-URL: Documentation, https://histoseg.readthedocs.io
Requires-Python: >=3.10
License-File: LICENSE
License-File: AUTHORS.rst
Dynamic: license-file
